{
    "name": "presence-cube.native",
    "description": "Composition root of the native platform branch of the presence-cube project. This project is responsible for wiring up the dependency tree and providing the applications entry point.",
    "version": "0.0.1",
    "platforms": [ "native" ],
    "srcDir": ".",
    "build": {
        "srcFilter": [
            "+<*.c>"
        ],
        "includeDir": "./"
    },
    "dependencies": {
        "logging.native": "*",
        "infrastructure.native": "*",
        "presence-cube.shared": "*"
    }
}
